CHANGES.txt
MANIFEST.in
README.md
setup.py
dockerfly/__init__.py
dockerfly/errors.py
dockerfly/logger.py
dockerfly/settings.py
dockerfly/version.txt
dockerfly.egg-info/PKG-INFO
dockerfly.egg-info/SOURCES.txt
dockerfly.egg-info/dependency_links.txt
dockerfly.egg-info/entry_points.txt
dockerfly.egg-info/requires.txt
dockerfly.egg-info/top_level.txt
dockerfly/bin/__init__.py
dockerfly/bin/dockerflyctl.py
dockerfly/bin/dockerflyd.py
dockerfly/bin/include.py
dockerfly/contrib/__init__.py
dockerfly/contrib/filelock.py
dockerfly/dockerlib/__init__.py
dockerfly/dockerlib/container.py
dockerfly/dockerlib/libs.py
dockerfly/dockernet/__init__.py
dockerfly/dockernet/veth.py
dockerfly/dockernet/tests/__init__.py
dockerfly/dockernet/tests/test_macvlan.py
dockerfly/http/__init__.py
dockerfly/http/error.py
dockerfly/http/include.py
dockerfly/http/server.py
dockerfly/runtime/__init__.py
dockerfly/runtime/container.py
dockerfly/runtime/database.py
dockerfly/runtime/ippool.py
dockerfly/runtime/template.py