Metadata-Version: 1.0
Name: dockerfly
Version: 1.3.0
Summary: a docker tool for create containers easily
Home-page: https://github.com/memoryboxes/dockerfly
Author: memoryboxes
Author-email: memoryboxes@gmail.com
License: BSD-derived (http://www.repoze.org/LICENSE.txt)
Keywords: docker,dockerfly
Platform: any
